<PAMDataset>
  <Metadata>
    <MDI key="DataType">Generic</MDI>
  </Metadata>
  <PAMRasterBand band="1">
    <Metadata>
      <MDI key="SourceBandIndex">0</MDI>
      <MDI key="STATISTICS_COVARIANCES">2189.509954881282</MDI>
      <MDI key="STATISTICS_EXCLUDEDVALUES"></MDI>
      <MDI key="STATISTICS_MAXIMUM">1468.6497802734</MDI>
      <MDI key="STATISTICS_MEAN">1362.0622113155</MDI>
      <MDI key="STATISTICS_MINIMUM">1217.5526123047</MDI>
      <MDI key="STATISTICS_SKIPFACTORX">1</MDI>
      <MDI key="STATISTICS_SKIPFACTORY">1</MDI>
      <MDI key="STATISTICS_STDDEV">46.792199722617</MDI>
    </Metadata>
  </PAMRasterBand>
</PAMDataset>
